{
    "application_id":  "APP-019",
    "document_id":  "APP-019-BNK-003",
    "document_type":  "bank_statement",
    "document_date":  "2026-01-28",
    "source_system":  "bank_statement",
    "party_role":  "borrower",
    "statement_month":  "2026-01",
    "owner_name":  "Evelyn Ross",
    "beginning_balance":  23887.50,
    "ending_balance":  28470.83,
    "average_balance":  26179.16,
    "total_deposits":  10083.33,
    "large_deposits":  [

                       ],
    "transactions":  [
                         {
                             "transaction_date":  "2026-01-10",
                             "description":  "Payroll",
                             "amount":  5041.66,
                             "category":  "payroll"
                         },
                         {
                             "transaction_date":  "2026-01-22",
                             "description":  "Payroll",
                             "amount":  5041.66,
                             "category":  "payroll"
                         },
                         {
                             "transaction_date":  "2026-01-18",
                             "description":  "Housing expense",
                             "amount":  -2200,
                             "category":  "housing"
                         },
                         {
                             "transaction_date":  "2026-01-19",
                             "description":  "Utilities",
                             "amount":  -380,
                             "category":  "utilities"
                         }
                     ]
}
